python_package_boilderplate/__init__.py
python_package_boilderplate/module.py
module_boilerplate-0.1.3.dist-info/METADATA
module_boilerplate-0.1.3.dist-info/WHEEL
module_boilerplate-0.1.3.dist-info/top_level.txt
module_boilerplate-0.1.3.dist-info/RECORD
