Metadata-Version: 2.4
Name: module_boilerplate
Version: 0.1.3
Home-page: https://github.com/SoyVitouPro/python-modules-boilerplate
Author: soyvitou
Author-email: soyvitoupro@gmail.com
Classifier: Programming Language :: Python :: 3
Classifier: License :: OSI Approved :: MIT License
Classifier: Operating System :: OS Independent
Requires-Python: >=3.6
Dynamic: author
Dynamic: author-email
Dynamic: classifier
Dynamic: description
Dynamic: description-content-type
Dynamic: home-page
Dynamic: requires-python
